verilog/alu.v
// this aboutta get complicated

module alu(
    input wire CLK,

    input wire [2:0] aindex,
    input wire [2:0] bindex,
    input wire [2:0] yindex,
    input wire [5:0] op,
    input wire [3:0] params,

    output reg overflow = 0
  );

  // verilator lint_off MULTIDRIVEN
  reg [15:0] r0 = 16'h1;
  reg [15:0] r1 = 16'h2;
  reg [15:0] r2 = 16'h3;
  reg [15:0] r3 = 16'h4;
  reg [15:0] r4 = 16'h5;
  reg [15:0] r5 = 16'h6;
  reg [15:0] r6 = 16'h7;
  reg [15:0] r7 = 16'h8;
  // verilator lint_on MULTIDRIVEN

  wire [16:0] addsub; // wire with overflow bit
  wire [16:0] mult;   // the overflow bit works just like addition
  wire [15:0] log;    // overflow not possible with bitwise logic
  reg [15:0] lshift;  // overflow unreliable
  reg [15:0] rshift;  // overflow unreliable

  reg [15:0] a = 16'b0;
  reg [15:0] b = 16'b0;

  always @(*) begin
    case (aindex)
      3'd0: a = r0;
      3'd1: a = r1;
      3'd2: a = r2;
      3'd3: a = r3;
      3'd4: a = r4;
      3'd5: a = r5;
      3'd6: a = r6;
      3'd7: a = r7;
    endcase
  end

  always @(*) begin
    case (bindex)
      3'd0: b = r0;
      3'd1: b = r1;
      3'd2: b = r2;
      3'd3: b = r3;
      3'd4: b = r4;
      3'd5: b = r5;
      3'd6: b = r6;
      3'd7: b = r7;
    endcase
  end

  // left shift
  always @(*) begin
    case (params)
      4'h0: lshift = a;
      4'h1: lshift = {a[14:0], 1'b0};
      4'h2: lshift = {a[13:0], 2'b0};
      4'h3: lshift = {a[12:0], 3'b0};
      4'h4: lshift = {a[11:0], 4'b0};
      4'h5: lshift = {a[10:0], 5'b0};
      4'h6: lshift = {a[9:0], 6'b0};
      4'h7: lshift = {a[8:0], 7'b0};
      4'h8: lshift = {a[7:0], 8'b0};
      4'h9: lshift = {a[6:0], 9'b0};
      4'hA: lshift = {a[5:0], 10'b0};
      4'hB: lshift = {a[4:0], 11'b0};
      4'hC: lshift = {a[3:0], 12'b0};
      4'hD: lshift = {a[2:0], 13'b0};
      4'hE: lshift = {a[1:0], 14'b0};
      4'hF: lshift = {a[0], 15'b0};
    endcase
  end

  always @(*) begin
    case (params)
      4'h0: rshift = a;
      4'h1: rshift = {1'b0, a[15:1]};
      4'h2: rshift = {2'b0, a[15:2]};
      4'h3: rshift = {3'b0, a[15:3]};
      4'h4: rshift = {4'b0, a[15:4]};
      4'h5: rshift = {5'b0, a[15:5]};
      4'h6: rshift = {6'b0, a[15:6]};
      4'h7: rshift = {7'b0, a[15:7]};
      4'h8: rshift = {8'b0, a[15:8]};
      4'h9: rshift = {9'b0, a[15:9]};
      4'hA: rshift = {10'b0, a[15:10]};
      4'hB: rshift = {11'b0, a[15:11]};
      4'hC: rshift = {12'b0, a[15:12]};
      4'hD: rshift = {13'b0, a[15:13]};
      4'hE: rshift = {14'b0, a[15:14]};
      4'hF: rshift = {15'b0, a[15]};
    endcase
  end

  // 0 = AND, 1 = OR, 2 = XOR, 3 = NOT
  assign log = params[1] & params[0] ? ~a : params[1] ?
               a ^ b : params[0] ? a | b : a & b;
  // assign log = op[0] ? a | b : op[1] ? a ^ b : a & b;
  assign addsub = params[0] ? a - b : a + b;
  assign mult = a*b;

  always @(negedge CLK) begin
    if (op[5]) begin
      if (op[0]) begin
        case (yindex)
          3'd0: r0 <= addsub[15:0];
          3'd1: r1 <= addsub[15:0];
          3'd2: r2 <= addsub[15:0];
          3'd3: r3 <= addsub[15:0];
          3'd4: r4 <= addsub[15:0];
          3'd5: r5 <= addsub[15:0];
          3'd6: r6 <= addsub[15:0];
          3'd7: r7 <= addsub[15:0];
        endcase
        overflow <= overflow | addsub[16];
      end else if (op[1]) begin
        case (yindex)
          3'd0: r0 <= mult[15:0];
          3'd1: r1 <= mult[15:0];
          3'd2: r2 <= mult[15:0];
          3'd3: r3 <= mult[15:0];
          3'd4: r4 <= mult[15:0];
          3'd5: r5 <= mult[15:0];
          3'd6: r6 <= mult[15:0];
          3'd7: r7 <= mult[15:0];
        endcase
        overflow <= overflow | mult[16];
      end else if (op[2]) begin
        case (yindex)
          3'd0: r0 <= log;
          3'd1: r1 <= log;
          3'd2: r2 <= log;
          3'd3: r3 <= log;
          3'd4: r4 <= log;
          3'd5: r5 <= log;
          3'd6: r6 <= log;
          3'd7: r7 <= log;
        endcase
      end else if (op[3]) begin
        case (yindex)
          3'd0: r0 <= lshift;
          3'd1: r1 <= lshift;
          3'd2: r2 <= lshift;
          3'd3: r3 <= lshift;
          3'd4: r4 <= lshift;
          3'd5: r5 <= lshift;
          3'd6: r6 <= lshift;
          3'd7: r7 <= lshift;
        endcase
      end else if (op[4]) begin
        case (yindex)
          3'd0: r0 <= rshift;
          3'd1: r1 <= rshift;
          3'd2: r2 <= rshift;
          3'd3: r3 <= rshift;
          3'd4: r4 <= rshift;
          3'd5: r5 <= rshift;
          3'd6: r6 <= rshift;
          3'd7: r7 <= rshift;
        endcase
      end
    end
  end

endmodule

verilog/uart.v
//parameter ClkFrequency = 12000000
//parameter Baud = 3000000
// 8 data bits, 1 stop bit, no parity

module uart(
    input CLK,
    input RX,
    input [7:0] TXbuffer,
    input TXstart,

    output TX,
    output reg [7:0] RXbuffer = 0,
    output reg RXready = 0,
    output TXbusy
  );

  parameter CLOCK_DIVISOR = 2; // 2 ^ CLOCK_DIVISOR

  // TRANSMITTER

  reg [CLOCK_DIVISOR:0] baudAcc = 0;
  wire baudTick = baudAcc[CLOCK_DIVISOR];

  reg [3:0] TXstate = 0;
  wire TXready = (TXstate==0);
  assign TXbusy = ~TXready;

  reg [7:0] TXshift = 0;

  always @(negedge CLK) begin

    if(TXready & TXstart) TXshift <= TXbuffer;
    else if(TXstate[3] & baudTick) TXshift <= (TXshift >> 1);

    if (TXstate == 4'b0000) baudAcc <= 0;
    else baudAcc <= baudAcc[CLOCK_DIVISOR - 1:0] + 1'b1;

    case(TXstate)
      4'b0000: if(TXstart)  TXstate <= 4'b0100;
      4'b0100: if(baudTick) TXstate <= 4'b1000; // start bit
      4'b1000: if(baudTick) TXstate <= 4'b1001; // bit 0
      4'b1001: if(baudTick) TXstate <= 4'b1010; // bit 1
      4'b1010: if(baudTick) TXstate <= 4'b1011; // bit 2
      4'b1011: if(baudTick) TXstate <= 4'b1100; // bit 3
      4'b1100: if(baudTick) TXstate <= 4'b1101; // bit 4
      4'b1101: if(baudTick) TXstate <= 4'b1110; // bit 5
      4'b1110: if(baudTick) TXstate <= 4'b1111; // bit 6
      4'b1111: if(baudTick) TXstate <= 4'b0001; // bit 7
      4'b0001: if(baudTick) TXstate <= 4'b0000; // stop bit
      default: if(baudTick) TXstate <= 4'b0000;
    endcase
  end

  assign TX = (TXstate < 4) | (TXstate[3] & TXshift[0]);

  // RECIEVER

  // Oversampling x 4 (i.e. every clock cycle)
  // Surprisingly reliable

  reg [3:0] RXstate = 0;
  reg [CLOCK_DIVISOR:0] gap = 0;

  wire nextBit = gap[CLOCK_DIVISOR];

  always @(negedge CLK) begin

    case (RXstate)
      4'b0000: if (~RX) RXstate <= 4'b1000;     // start bit found
      4'b1000: if (nextBit) RXstate <= 4'b1001; // bit 0
      4'b1001: if (nextBit) RXstate <= 4'b1010; // bit 1
      4'b1010: if (nextBit) RXstate <= 4'b1011; // bit 2
      4'b1011: if (nextBit) RXstate <= 4'b1100; // bit 3
      4'b1100: if (nextBit) RXstate <= 4'b1101; // bit 4
      4'b1101: if (nextBit) RXstate <= 4'b1110; // bit 5
      4'b1110: if (nextBit) RXstate <= 4'b1111; // bit 6
      4'b1111: if (nextBit) RXstate <= 4'b0001; // bit 7
      4'b0001: if (nextBit) RXstate <= 4'b0000; // stop bit
      default: RXstate <= 4'b0000;
    endcase

    if (RXstate == 4'b0000) begin
      gap <= 0;
    end else gap <= gap[CLOCK_DIVISOR - 1:0] + 1'b1;

    if (nextBit && RXstate[3]) RXbuffer <= {RX, RXbuffer[7:1]};
    RXready <= (nextBit && RXstate == 4'b0001);
  end

endmodule

verilog/top.v
//verilator lint_off UNUSED

`timescale 1ns/100ps
`default_nettype none

`include "uart.v"
`include "alu.v"

module top(
    input wire CLK,

    input wire RX,
    output wire TX,

    // output wire GPIO0,
    // output wire GPIO1,
    // output wire GPIO2,
    output wire GPIO3,
    output wire GPIO9,
    output wire GPIO11
  );

  // UART communication
  wire [7:0] RXbuffer;
  reg [7:0] TXbuffer = 0;
  reg TXstart = 0;
  wire RXready;
  wire TXbusy;

  uart FTDI(
      .CLK(CLK),
      .RX(RX),
      .TXbuffer(TXbuffer),
      .TXstart(TXstart),
      .TX(TX),
      .RXbuffer(RXbuffer),
      .RXready(RXready),
      .TXbusy(TXbusy)
    );

  // ALU
  reg [2:0] a = 3'b000; // temporary hack for a SEC!!!!
  reg [2:0] b = 3'b001;
  reg [2:0] y = 0;
  reg [5:0] op = 6'h0;
  reg [3:0] params = 4'h0;
  //wire [15:0] res;
  wire overflow;

  alu ALU(
      .CLK(CLK),
      .aindex(a),
      .bindex(b),
      .yindex(y),
      .op(op),
      .params(params),
      .overflow(overflow)
    );

  reg [3:0] testState = 0;
  reg [24:0] clkdiv = 0;

  always @(posedge CLK) begin

    clkdiv <= clkdiv + 1'b1;
    // testState <= testState + 1'b1;
    //
    // if (clkdiv[3:0] == 4'd15) begin
    //   params <= params + 1'b1;
    //   a <= a + 1'b1;
    //   b <= b + 1'b1;
    //   y <= y + 1'b1;
    //   TXstart <= 1'b1;
    //   op <= op + 1'b1;
    //   case (clkdiv[7:4]) // forcing icecube to synthesize
    //     4'd0: TXbuffer <= ALU.r0[7:0];
    //     4'd1: TXbuffer <= ALU.r1[7:0];
    //     4'd2: TXbuffer <= ALU.r2[7:0];
    //     4'd3: TXbuffer <= ALU.r3[7:0];
    //     4'd4: TXbuffer <= ALU.r4[7:0];
    //     4'd5: TXbuffer <= ALU.r5[7:0];
    //     4'd6: TXbuffer <= ALU.r6[7:0];
    //     4'd7: TXbuffer <= ALU.r7[7:0];
    //     4'd8: TXbuffer <= ALU.r0[15:8];
    //     4'd9: TXbuffer <= ALU.r1[15:8];
    //     4'd10: TXbuffer <= ALU.r2[15:8];
    //     4'd11: TXbuffer <= ALU.r3[15:8];
    //     4'd12: TXbuffer <= ALU.r4[15:8];
    //     4'd13: TXbuffer <= ALU.r5[15:8];
    //     4'd14: TXbuffer <= ALU.r6[15:8];
    //     4'd15: TXbuffer <= ALU.r7[15:8];
    //   endcase
    //   // a <= 0;
    // end else TXstart <= 1'b0;

    case (testState)
      4'd0:
        begin
          TXstart <= 1'b0;
          if (RXready) begin
            op <= RXbuffer[5:0];
            testState <= 4'd8;
          end
        end
      4'd8:
        begin
          if (RXready) begin
            params <= RXbuffer[3:0];
            testState <= 4'd1;
          end
        end
      4'd1:
        begin
          if (RXready) begin
            ALU.r0[7:0] <= RXbuffer;
            testState <= 4'd2;
          end
        end
      4'd2:
        begin
          if (RXready) begin
            ALU.r0[15:8] <= RXbuffer;
            testState <= 4'd3;
          end
        end
      4'd3:
        begin
          if (RXready) begin
            ALU.r1[7:0] <= RXbuffer;
            testState <= 4'd4;
          end
        end
      4'd4:
        begin
          if (RXready) begin
            ALU.r1[15:8] <= RXbuffer;
            testState <= 4'd5;
            op[5] <= 1'b1;
          end
        end
      4'd5:
        begin
          if (~TXbusy) begin
            op[5] <= 1'b0;
            TXbuffer <= ALU.r0[7:0];
            TXstart <= 1'b1;
            testState <= 4'd6;
          end
        end
      4'd6:
        begin
          TXstart <= 1'b0;
          if (~TXbusy) begin
            TXbuffer <= ALU.r0[15:8];
            TXstart <= 1'b1;
            testState <= 4'd7;
          end
        end
      4'd7:
        begin
          TXstart <= 1'b0;
          if (~TXbusy) begin
            TXbuffer <= {7'd0, overflow};
            TXstart <= 1'b1;
            testState <= 4'd0;
          end
        end
      default:
        begin
          TXstart <= 1'b0;
          testState <= 4'd0;
        end
    endcase
   end

  assign GPIO9 = 1'b1;
  assign GPIO11 = 1'b0;

  // assign GPIO0 = res[0];
  // assign GPIO1 = res[1];
  // assign GPIO2 = res[2];
  assign GPIO3 = clkdiv[23];

endmodule

trace.vcd
$version Generated by VerilatedVcd $end
$date Sat Aug 15 15:53:12 2020
 $end
$timescale 100ps $end

 $scope module TOP $end
  $var wire  1 C CLK $end
  $var wire  1 H GPIO11 $end
  $var wire  1 F GPIO3 $end
  $var wire  1 G GPIO9 $end
  $var wire  1 D RX $end
  $var wire  1 E TX $end
  $scope module top $end
   $var wire  1 C CLK $end
   $var wire  1 H GPIO11 $end
   $var wire  1 F GPIO3 $end
   $var wire  1 G GPIO9 $end
   $var wire  1 D RX $end
   $var wire  8 ) RXbuffer [7:0] $end
   $var wire  1 * RXready $end
   $var wire  1 E TX $end
   $var wire  8 5 TXbuffer [7:0] $end
   $var wire  1 + TXbusy $end
   $var wire  1 6 TXstart $end
   $var wire  3 J a [2:0] $end
   $var wire  3 K b [2:0] $end
   $var wire 25 I clkdiv [24:0] $end
   $var wire  6 7 op [5:0] $end
   $var wire  1 , overflow $end
   $var wire  4 8 params [3:0] $end
   $var wire  4 9 testState [3:0] $end
   $var wire  3 J y [2:0] $end
   $scope module ALU $end
    $var wire  1 C CLK $end
    $var wire 16 B a [15:0] $end
    $var wire 17 = addsub [16:0] $end
    $var wire  3 J aindex [2:0] $end
    $var wire 16 ; b [15:0] $end
    $var wire  3 K bindex [2:0] $end
    $var wire 16 ? log [15:0] $end
    $var wire 16 @ lshift [15:0] $end
    $var wire 17 > mult [16:0] $end
    $var wire  6 7 op [5:0] $end
    $var wire  1 , overflow $end
    $var wire  4 8 params [3:0] $end
    $var wire 16 < r0 [15:0] $end
    $var wire 16 : r1 [15:0] $end
    $var wire 16 # r2 [15:0] $end
    $var wire 16 $ r3 [15:0] $end
    $var wire 16 % r4 [15:0] $end
    $var wire 16 & r5 [15:0] $end
    $var wire 16 ' r6 [15:0] $end
    $var wire 16 ( r7 [15:0] $end
    $var wire 16 A rshift [15:0] $end
    $var wire  3 J yindex [2:0] $end
   $upscope $end
   $scope module FTDI $end
    $var wire  1 C CLK $end
    $var wire 32 L CLOCK_DIVISOR [31:0] $end
    $var wire  1 D RX $end
    $var wire  8 ) RXbuffer [7:0] $end
    $var wire  1 * RXready $end
    $var wire  4 2 RXstate [3:0] $end
    $var wire  1 E TX $end
    $var wire  8 5 TXbuffer [7:0] $end
    $var wire  1 + TXbusy $end
    $var wire  1 0 TXready $end
    $var wire  8 1 TXshift [7:0] $end
    $var wire  1 6 TXstart $end
    $var wire  4 / TXstate [3:0] $end
    $var wire  3 - baudAcc [2:0] $end
    $var wire  1 . baudTick $end
    $var wire  3 3 gap [2:0] $end
    $var wire  1 4 nextBit $end
   $upscope $end
  $upscope $end
 $upscope $end
$enddefinitions $end


#666
b0000000000000011 #
b0000000000000100 $
b0000000000000101 %
b0000000000000110 &
b0000000000000111 '
b0000000000001000 (
b00000000 )
0*
0+
0,
b000 -
0.
b0000 /
10
b00000000 1
b0000 2
b000 3
04
b00000000 5
06
b000000 7
b0000 8
b0000 9
b0000000000000010 :
b0000000000000010 ;
b0000000000000001 <
b00000000000000011 =
b00000000000000010 >
b0000000000000000 ?
b0000000000000001 @
b0000000000000001 A
b0000000000000001 B
0C
1D
1E
0F
1G
0H
b0000000000000000000000000 I
b000 J
b001 K
b00000000000000000000000000000010 L
#833
1C
b0000000000000000000000001 I
#1250
0C
#1499
#1666
1C
b0000000000000000000000010 I
#2083
0C
#2333
#2500
1C
b0000000000000000000000011 I
#2916
0C
#3166
#3333
1C
b0000000000000000000000100 I
#3749
0C
#3999
0D
#4166
1C
b0000000000000000000000101 I
#4583
b1000 2
0C
#4833
#5000
1C
b0000000000000000000000110 I
#5416
b001 3
0C
#5666
#5833
1C
b0000000000000000000000111 I
#6249
b010 3
0C
#6499
#6666
1C
b0000000000000000000001000 I
#7083
b011 3
0C
#7333
#7500
1C
b0000000000000000000001001 I
#7916
b100 3
14
0C
#8166
#8333
1C
b0000000000000000000001010 I
#8749
b1001 2
b001 3
04
0C
#9000
#9166
1C
b0000000000000000000001011 I
#9583
b010 3
0C
#9833
#10000
1C
b0000000000000000000001100 I
#10416
b011 3
0C
#10666
#10833
1C
b0000000000000000000001101 I
#11249
b100 3
14
0C
#11499
#11666
1C
b0000000000000000000001110 I
#12083
b1010 2
b001 3
04
0C
#12333
#12500
1C
b0000000000000000000001111 I
#12916
b010 3
0C
#13166
#13333
1C
b0000000000000000000010000 I
#13749
b011 3
0C
#13999
#14166
1C
b0000000000000000000010001 I
#14583
b100 3
14
0C
#14833
#15000
1C
b0000000000000000000010010 I
#15416
b1011 2
b001 3
04
0C
#15666
#15833
1C
b0000000000000000000010011 I
#16249
b010 3
0C
#16499
#16666
1C
b0000000000000000000010100 I
#17083
b011 3
0C
#17333
#17500
1C
b0000000000000000000010101 I
#17916
b100 3
14
0C
#18166
#18333
1C
b0000000000000000000010110 I
#18750
b1100 2
b001 3
04
0C
#18999
#19166
1C
b0000000000000000000010111 I
#19583
b010 3
0C
#19833
#20000
1C
b0000000000000000000011000 I
#20416
b011 3
0C
#20666
1D
#20833
1C
b0000000000000000000011001 I
#21249
b100 3
14
0C
#21499
#21666
1C
b0000000000000000000011010 I
#22083
b10000000 )
b1101 2
b001 3
04
0C
#22333
#22500
1C
b0000000000000000000011011 I
#22916
b010 3
0C
#23166
#23333
1C
b0000000000000000000011100 I
#23749
b011 3
0C
#23999
0D
#24166
1C
b0000000000000000000011101 I
#24583
b100 3
14
0C
#24833
#25000
1C
b0000000000000000000011110 I
#25416
b01000000 )
b1110 2
b001 3
04
0C
#25666
#25833
1C
b0000000000000000000011111 I
#26249
b010 3
0C
#26499
#26666
1C
b0000000000000000000100000 I
#27083
b011 3
0C
#27333
#27500
1C
b0000000000000000000100001 I
#27916
b100 3
14
0C
#28166
#28333
1C
b0000000000000000000100010 I
#28749
b00100000 )
b1111 2
b001 3
04
0C
#28999
#29166
1C
b0000000000000000000100011 I
#29583
b010 3
0C
#29833
#30000
1C
b0000000000000000000100100 I
#30416
b011 3
0C
#30666
#30833
1C
b0000000000000000000100101 I
#31249
b100 3
14
0C
#31499
#31666
1C
b0000000000000000000100110 I
#32083
b00010000 )
b0001 2
b001 3
04
0C
#32333
#32500
1C
b0000000000000000000100111 I
#32916
b010 3
0C
#33166
#33333
1C
b0000000000000000000101000 I
#33749
b011 3
0C
#34000
1D
#34166
1C
b0000000000000000000101001 I
#34583
b100 3
14
0C
#34833
#35000
1C
b0000000000000000000101010 I
#35416
1*
b0000 2
b001 3
04
0C
#35666
#35833
b010000 7
b1000 9
1C
b0000000000000000000101011 I
#36249
0*
b000 3
0C
#36500
#36666
1C
b0000000000000000000101100 I
#37083
0C
#37333
0D
#37500
1C
b0000000000000000000101101 I
#37916
b1000 2
0C
#38166
#38333
1C
b0000000000000000000101110 I
#38749
b001 3
0C
#39000
#39166
1C
b0000000000000000000101111 I
#39583
b010 3
0C
#39833
#40000
1C
b0000000000000000000110000 I
#40416
b011 3
0C
#40666
#40833
1C
b0000000000000000000110001 I
#41249
b100 3
14
0C
#41499
#41666
1C
b0000000000000000000110010 I
#42083
b00001000 )
b1001 2
b001 3
04
0C
#42333
#42500
1C
b0000000000000000000110011 I
#42916
b010 3
0C
#43166
#43333
1C
b0000000000000000000110100 I
#43749
b011 3
0C
#43999
#44166
1C
b0000000000000000000110101 I
#44583
b100 3
14
0C
#44833
#45000
1C
b0000000000000000000110110 I
#45416
b00000100 )
b1010 2
b001 3
04
0C
#45666
#45833
1C
b0000000000000000000110111 I
#46249
b010 3
0C
#46499
#46666
1C
b0000000000000000000111000 I
#47083
b011 3
0C
#47333
1D
#47500
1C
b0000000000000000000111001 I
#47916
b100 3
14
0C
#48166
#48333
1C
b0000000000000000000111010 I
#48749
b10000010 )
b1011 2
b001 3
04
0C
#48999
#49166
1C
b0000000000000000000111011 I
#49583
b010 3
0C
#49833
#50000
1C
b0000000000000000000111100 I
#50416
b011 3
0C
#50666
0D
#50833
1C
b0000000000000000000111101 I
#51249
b100 3
14
0C
#51499
#51666
1C
b0000000000000000000111110 I
#52083
b01000001 )
b1100 2
b001 3
04
0C
#52333
#52500
1C
b0000000000000000000111111 I
#52916
b010 3
0C
#53166
#53333
1C
b0000000000000000001000000 I
#53749
b011 3
0C
#53999
#54166
1C
b0000000000000000001000001 I
#54583
b100 3
14
0C
#54833
#55000
1C
b0000000000000000001000010 I
#55416
b00100000 )
b1101 2
b001 3
04
0C
#55666
#55833
1C
b0000000000000000001000011 I
#56249
b010 3
0C
#56499
#56666
1C
b0000000000000000001000100 I
#57083
b011 3
0C
#57333
#57500
1C
b0000000000000000001000101 I
#57916
b100 3
14
0C
#58166
#58333
1C
b0000000000000000001000110 I
#58749
b00010000 )
b1110 2
b001 3
04
0C
#58999
#59166
1C
b0000000000000000001000111 I
#59583
b010 3
0C
#59833
#60000
1C
b0000000000000000001001000 I
#60416
b011 3
0C
#60666
#60833
1C
b0000000000000000001001001 I
#61249
b100 3
14
0C
#61499
#61666
1C
b0000000000000000001001010 I
#62083
b00001000 )
b1111 2
b001 3
04
0C
#62333
#62500
1C
b0000000000000000001001011 I
#62916
b010 3
0C
#63166
#63333
1C
b0000000000000000001001100 I
#63749
b011 3
0C
#63999
#64166
1C
b0000000000000000001001101 I
#64583
b100 3
14
0C
#64833
#65000
1C
b0000000000000000001001110 I
#65416
b00000100 )
b0001 2
b001 3
04
0C
#65666
#65833
1C
b0000000000000000001001111 I
#66250
b010 3
0C
#66499
#66666
1C
b0000000000000000001010000 I
#67083
b011 3
0C
#67333
1D
#67500
1C
b0000000000000000001010001 I
#67916
b100 3
14
0C
#68166
#68333
1C
b0000000000000000001010010 I
#68750
1*
b0000 2
b001 3
04
0C
#68999
#69166
b0100 8
b0001 9
b0000000000010000 @
b0000000000000000 A
1C
b0000000000000000001010011 I
#69583
0*
b000 3
0C
#69833
#70000
1C
b0000000000000000001010100 I
#70416
0C
#70666
0D
#70833
1C
b0000000000000000001010101 I
#71250
b1000 2
0C
#71499
#71666
1C
b0000000000000000001010110 I
#72083
b001 3
0C
#72333
#72500
1C
b0000000000000000001010111 I
#72916
b010 3
0C
#73166
#73333
1C
b0000000000000000001011000 I
#73750
b011 3
0C
#73999
#74166
1C
b0000000000000000001011001 I
#74583
b100 3
14
0C
#74833
#75000
1C
b0000000000000000001011010 I
#75416
b00000010 )
b1001 2
b001 3
04
0C
#75666
#75833
1C
b0000000000000000001011011 I
#76250
b010 3
0C
#76499
#76666
1C
b0000000000000000001011100 I
#77083
b011 3
0C
#77333
#77500
1C
b0000000000000000001011101 I
#77916
b100 3
14
0C
#78166
#78333
1C
b0000000000000000001011110 I
#78750
b00000001 )
b1010 2
b001 3
04
0C
#78999
#79166
1C
b0000000000000000001011111 I
#79583
b010 3
0C
#79833
#80000
1C
b0000000000000000001100000 I
#80416
b011 3
0C
#80666
#80833
1C
b0000000000000000001100001 I
#81250
b100 3
14
0C
#81499
#81666
1C
b0000000000000000001100010 I
#82083
b00000000 )
b1011 2
b001 3
04
0C
#82333
#82500
1C
b0000000000000000001100011 I
#82916
b010 3
0C
#83166
#83333
1C
b0000000000000000001100100 I
#83749
b011 3
0C
#83999
#84166
1C
b0000000000000000001100101 I
#84583
b100 3
14
0C
#84833
#85000
1C
b0000000000000000001100110 I
#85416
b1100 2
b001 3
04
0C
#85666
#85833
1C
b0000000000000000001100111 I
#86249
b010 3
0C
#86499
#86666
1C
b0000000000000000001101000 I
#87083
b011 3
0C
#87333
#87500
1C
b0000000000000000001101001 I
#87916
b100 3
14
0C
#88166
#88333
1C
b0000000000000000001101010 I
#88749
b1101 2
b001 3
04
0C
#88999
#89166
1C
b0000000000000000001101011 I
#89583
b010 3
0C
#89833
#90000
1C
b0000000000000000001101100 I
#90416
b011 3
0C
#90666
#90833
1C
b0000000000000000001101101 I
#91249
b100 3
14
0C
#91499
#91666
1C
b0000000000000000001101110 I
#92083
b1110 2
b001 3
04
0C
#92333
#92500
1C
b0000000000000000001101111 I
#92916
b010 3
0C
#93166
#93333
1C
b0000000000000000001110000 I
#93749
b011 3
0C
#93999
#94166
1C
b0000000000000000001110001 I
#94583
b100 3
14
0C
#94833
#95000
1C
b0000000000000000001110010 I
#95416
b1111 2
b001 3
04
0C
#95666
#95833
1C
b0000000000000000001110011 I
#96249
b010 3
0C
#96499
#96666
1C
b0000000000000000001110100 I
#97083
b011 3
0C
#97333
#97500
1C
b0000000000000000001110101 I
#97916
b100 3
14
0C
#98166
#98333
1C
b0000000000000000001110110 I
#98749
b0001 2
b001 3
04
0C
#98999
#99166
1C
b0000000000000000001110111 I
#99583
b010 3
0C
#99833
#100000
1C
b0000000000000000001111000 I
#100416
b011 3
0C
#100666
1D
#100833
1C
b0000000000000000001111001 I
#101249
b100 3
14
0C
#101499
#101666
1C
b0000000000000000001111010 I
#102083
1*
b0000 2
b001 3
04
0C
#102333
#102500
b0010 9
b0000000000000000 <
b00000000000000010 =
b00000000000000000 >
b0000000000000000 @
b0000000000000000 B
1C
b0000000000000000001111011 I
#102916
0*
b000 3
0C
#103166
#103333
1C
b0000000000000000001111100 I
#103749
0C
#103999
0D
#104166
1C
b0000000000000000001111101 I
#104583
b1000 2
0C
#104833
#105000
1C
b0000000000000000001111110 I
#105416
b001 3
0C
#105666
#105833
1C
b0000000000000000001111111 I
#106249
b010 3
0C
#106499
#106666
1C
b0000000000000000010000000 I
#107083
b011 3
0C
#107333
1D
#107500
1C
b0000000000000000010000001 I
#107916
b100 3
14
0C
#108166
#108333
1C
b0000000000000000010000010 I
#108749
b10000000 )
b1001 2
b001 3
04
0C
#108999
#109166
1C
b0000000000000000010000011 I
#109583
b010 3
0C
#109833
#110000
1C
b0000000000000000010000100 I
#110416
b011 3
0C
#110666
0D
#110833
1C
b0000000000000000010000101 I
#111249
b100 3
14
0C
#111499
#111666
1C
b0000000000000000010000110 I
#112083
b01000000 )
b1010 2
b001 3
04
0C
#112333
#112500
1C
b0000000000000000010000111 I
#112916
b010 3
0C
#113166
#113333
1C
b0000000000000000010001000 I
#113749
b011 3
0C
#113999
#114166
1C
b0000000000000000010001001 I
#114583
b100 3
14
0C
#114833
#115000
1C
b0000000000000000010001010 I
#115416
b00100000 )
b1011 2
b001 3
04
0C
#115666
#115833
1C
b0000000000000000010001011 I
#116249
b010 3
0C
#116499
#116666
1C
b0000000000000000010001100 I
#117083
b011 3
0C
#117333
#117500
1C
b0000000000000000010001101 I
#117916
b100 3
14
0C
#118166
#118333
1C
b0000000000000000010001110 I
#118749
b00010000 )
b1100 2
b001 3
04
0C
#118999
#119166
1C
b0000000000000000010001111 I
#119583
b010 3
0C
#119833
#120000
1C
b0000000000000000010010000 I
#120416
b011 3
0C
#120666
#120833
1C
b0000000000000000010010001 I
#121249
b100 3
14
0C
#121499
#121666
1C
b0000000000000000010010010 I
#122083
b00001000 )
b1101 2
b001 3
04
0C
#122333
#122500
1C
b0000000000000000010010011 I
#122916
b010 3
0C
#123166
#123333
1C
b0000000000000000010010100 I
#123749
b011 3
0C
#123999
#124166
1C
b0000000000000000010010101 I
#124583
b100 3
14
0C
#124833
#125000
1C
b0000000000000000010010110 I
#125416
b00000100 )
b1110 2
b001 3
04
0C
#125666
#125833
1C
b0000000000000000010010111 I
#126249
b010 3
0C
#126499
#126666
1C
b0000000000000000010011000 I
#127083
b011 3
0C
#127333
#127500
1C
b0000000000000000010011001 I
#127916
b100 3
14
0C
#128166
#128333
1C
b0000000000000000010011010 I
#128749
b00000010 )
b1111 2
b001 3
04
0C
#128999
#129166
1C
b0000000000000000010011011 I
#129583
b010 3
0C
#129833
#130000
1C
b0000000000000000010011100 I
#130416
b011 3
0C
#130666
#130833
1C
b0000000000000000010011101 I
#131249
b100 3
14
0C
#131500
#131666
1C
b0000000000000000010011110 I
#132083
b00000001 )
b0001 2
b001 3
04
0C
#132333
#132500
1C
b0000000000000000010011111 I
#132916
b010 3
0C
#133166
#133333
1C
b0000000000000000010100000 I
#133749
b011 3
0C
#134000
1D
#134166
1C
b0000000000000000010100001 I
#134583
b100 3
14
0C
#134833
#135000
1C
b0000000000000000010100010 I
#135416
1*
b0000 2
b001 3
04
0C
#135666
#135833
b0011 9
b0000000100000000 <
b00000000100000010 =
b00000001000000000 >
b0001000000000000 @
b0000000000010000 A
b0000000100000000 B
1C
b0000000000000000010100011 I
#136249
0*
b000 3
0C
#136500
#136666
1C
b0000000000000000010100100 I
#137083
0C
#137333
0D
#137500
1C
b0000000000000000010100101 I
#137916
b1000 2
0C
#138166
#138333
1C
b0000000000000000010100110 I
#138749
b001 3
0C
#139000
#139166
1C
b0000000000000000010100111 I
#139583
b010 3
0C
#139833
#140000
1C
b0000000000000000010101000 I
#140416
b011 3
0C
#140666
1D
#140833
1C
b0000000000000000010101001 I
#141249
b100 3
14
0C
#141500
#141666
1C
b0000000000000000010101010 I
#142083
b10000000 )
b1001 2
b001 3
04
0C
#142333
#142500
1C
b0000000000000000010101011 I
#142916
b010 3
0C
#143166
#143333
1C
b0000000000000000010101100 I
#143749
b011 3
0C
#144000
#144166
1C
b0000000000000000010101101 I
#144583
b100 3
14
0C
#144833
#145000
1C
b0000000000000000010101110 I
#145416
b11000000 )
b1010 2
b001 3
04
0C
#145666
#145833
1C
b0000000000000000010101111 I
#146249
b010 3
0C
#146500
#146666
1C
b0000000000000000010110000 I
#147083
b011 3
0C
#147333
0D
#147500
1C
b0000000000000000010110001 I
#147916
b100 3
14
0C
#148166
#148333
1C
b0000000000000000010110010 I
#148749
b01100000 )
b1011 2
b001 3
04
0C
#149000
#149166
1C
b0000000000000000010110011 I
#149583
b010 3
0C
#149833
#150000
1C
b0000000000000000010110100 I
#150416
b011 3
0C
#150666
