verilog/alu.v

module alu(
    input wire CLK,

    input wire [15:0] a, // bus architecture?
    input wire [15:0] b,
    input wire [1:0] op,


    output reg [15:0] res = 0,
    output reg overflow = 0
  );

  wire [16:0] addsub; // wire with overflow bit
  wire[16:0] mult; // the overflow bit works just like addition

  assign addsub = op[0] ? a - b : a + b;
  assign mult = a*b;

  always @(posedge CLK) begin
    if (~op[1]) begin
      res <= addsub[15:0];
      overflow <= addsub[16];
    end else begin
      res <= mult[15:0];
      overflow <= mult[16];
      // if (mult[31:16] > 0) overflow <= 1'b1;
      // else overflow <= 1'b0;
    end
  end

endmodule

verilog/uart.v
//parameter ClkFrequency = 12000000
//parameter Baud = 3000000
// 8 data bits, 1 stop bit, no parity

module uart(
    input CLK,
    input RX,
    input [7:0] TXbuffer,
    input TXstart,

    output TX,
    output reg [7:0] RXbuffer = 0,
    output reg RXready = 0,
    output TXbusy
  );

  parameter CLOCK_DIVISOR = 2; // 2 ^ CLOCK_DIVISOR

  // TRANSMITTER

  reg [CLOCK_DIVISOR:0] baudAcc = 0;
  wire baudTick = baudAcc[CLOCK_DIVISOR];

  reg [3:0] TXstate = 0;
  wire TXready = (TXstate==0);
  assign TXbusy = ~TXready;

  reg [7:0] TXshift = 0;

  always @(negedge CLK) begin

    if(TXready & TXstart) TXshift <= TXbuffer;
    else if(TXstate[3] & baudTick) TXshift <= (TXshift >> 1);

    if (TXstate == 4'b0000) baudAcc <= 0;
    else baudAcc <= baudAcc[CLOCK_DIVISOR - 1:0] + 1'b1;

    case(TXstate)
      4'b0000: if(TXstart)  TXstate <= 4'b0100;
      4'b0100: if(baudTick) TXstate <= 4'b1000; // start bit
      4'b1000: if(baudTick) TXstate <= 4'b1001; // bit 0
      4'b1001: if(baudTick) TXstate <= 4'b1010; // bit 1
      4'b1010: if(baudTick) TXstate <= 4'b1011; // bit 2
      4'b1011: if(baudTick) TXstate <= 4'b1100; // bit 3
      4'b1100: if(baudTick) TXstate <= 4'b1101; // bit 4
      4'b1101: if(baudTick) TXstate <= 4'b1110; // bit 5
      4'b1110: if(baudTick) TXstate <= 4'b1111; // bit 6
      4'b1111: if(baudTick) TXstate <= 4'b0001; // bit 7
      4'b0001: if(baudTick) TXstate <= 4'b0000; // stop bit
      default: if(baudTick) TXstate <= 4'b0000;
    endcase
  end

  assign TX = (TXstate < 4) | (TXstate[3] & TXshift[0]);

  // RECIEVER

  // Oversampling x 4 (i.e. every clock cycle)
  // Surprisingly reliable

  reg [3:0] RXstate = 0;
  reg [CLOCK_DIVISOR:0] gap = 0;

  wire nextBit = gap[CLOCK_DIVISOR];

  always @(negedge CLK) begin

    case (RXstate)
      4'b0000: if (~RX) RXstate <= 4'b1000;     // start bit found
      4'b1000: if (nextBit) RXstate <= 4'b1001; // bit 0
      4'b1001: if (nextBit) RXstate <= 4'b1010; // bit 1
      4'b1010: if (nextBit) RXstate <= 4'b1011; // bit 2
      4'b1011: if (nextBit) RXstate <= 4'b1100; // bit 3
      4'b1100: if (nextBit) RXstate <= 4'b1101; // bit 4
      4'b1101: if (nextBit) RXstate <= 4'b1110; // bit 5
      4'b1110: if (nextBit) RXstate <= 4'b1111; // bit 6
      4'b1111: if (nextBit) RXstate <= 4'b0001; // bit 7
      4'b0001: if (nextBit) RXstate <= 4'b0000; // stop bit
      default: RXstate <= 4'b0000;
    endcase

    if (RXstate == 4'b0000) begin
      gap <= 0;
    end else gap <= gap[CLOCK_DIVISOR - 1:0] + 1'b1;

    if (nextBit && RXstate[3]) RXbuffer <= {RX, RXbuffer[7:1]};
    RXready <= (nextBit && RXstate == 4'b0001);
  end

endmodule

verilog/top.v
//verilator lint_off UNUSED

`timescale 1ns/100ps
`default_nettype none

`include "uart.v"
`include "alu.v"

module top(
    input wire CLK,

    input wire RX,
    output wire TX,

    output wire GPIO0,
    output wire GPIO1,
    output wire GPIO2,
    output wire GPIO3,
    output wire GPIO9,
    output wire GPIO11
  );

  // UART communication
  wire [7:0] RXbuffer;
  reg [7:0] TXbuffer = 0;
  reg TXstart = 0;
  wire RXready;
  wire TXbusy;

  uart FTDI(
      .CLK(CLK),
      .RX(RX),
      .TXbuffer(TXbuffer),
      .TXstart(TXstart),
      .TX(TX),
      .RXbuffer(RXbuffer),
      .RXready(RXready),
      .TXbusy(TXbusy)
    );

  // ALU
  reg [15:0] a = 0;
  reg [15:0] b = 16'd4096;
  reg [1:0] op = 2'b10;
  wire [15:0] res;
  wire overflow;

  alu ALU(
      .CLK(CLK),
      .a(a),
      .b(b),
      .op(op),
      .res(res),
      .overflow(overflow)
    );

  reg [3:0] testState = 0;
  reg [24:0] clkdiv = 0;

  always @(posedge CLK) begin

    clkdiv <= clkdiv + 1'b1;
    // testState <= testState + 1'b1;
    //
    // if (a[5]) begin
    //   op <= op + 1'b1;
    //   b <= b + 1'b1;
    //   a <= 0;
    // end else begin
    //   a <= a + 1'b1;
    // end

    case (testState)
      4'd0:
        begin
          TXstart <= 1'b0;
          if (RXready) begin
            op <= RXbuffer[1:0];
            testState <= 4'd1;
          end
        end
      4'd1:
        begin
          if (RXready) begin
            a[7:0] <= RXbuffer;
            testState <= 4'd2;
          end
        end
      4'd2:
        begin
          if (RXready) begin
            a[15:8] <= RXbuffer;
            testState <= 4'd3;
          end
        end
      4'd3:
        begin
          if (RXready) begin
            b[7:0] <= RXbuffer;
            testState <= 4'd4;
          end
        end
      4'd4:
        begin
          if (RXready) begin
            b[15:8] <= RXbuffer;
            testState <= 4'd5;
          end
        end
      4'd5:
        begin
          if (~TXbusy) begin
            TXbuffer <= res[7:0];
            TXstart <= 1'b1;
            testState <= 4'd6;
          end
        end
      4'd6:
        begin
          TXstart <= 1'b0;
          if (~TXbusy) begin
            TXbuffer <= res[15:8];
            TXstart <= 1'b1;
            testState <= 4'd7;
          end
        end
      4'd7:
        begin
          TXstart <= 1'b0;
          if (~TXbusy) begin
            TXbuffer <= {7'd0, overflow};
            TXstart <= 1'b1;
            testState <= 4'd0;
          end
        end
      default:
        begin
          TXstart <= 1'b0;
          testState <= 4'd0;
        end
    endcase
  end

  assign GPIO9 = 1'b1;
  assign GPIO11 = 1'b0;

  assign GPIO0 = res[0];
  assign GPIO1 = res[1];
  assign GPIO2 = res[2];
  assign GPIO3 = clkdiv[23];

endmodule

trace.vcd
$version Generated by VerilatedVcd $end
$date Fri Aug 14 13:59:59 2020
 $end
$timescale 100ps $end

 $scope module TOP $end
  $var wire  1 9 CLK $end
  $var wire  1 < GPIO0 $end
  $var wire  1 = GPIO1 $end
  $var wire  1 A GPIO11 $end
  $var wire  1 > GPIO2 $end
  $var wire  1 ? GPIO3 $end
  $var wire  1 @ GPIO9 $end
  $var wire  1 : RX $end
  $var wire  1 ; TX $end
  $scope module top $end
   $var wire  1 9 CLK $end
   $var wire  1 < GPIO0 $end
   $var wire  1 = GPIO1 $end
   $var wire  1 A GPIO11 $end
   $var wire  1 > GPIO2 $end
   $var wire  1 ? GPIO3 $end
   $var wire  1 @ GPIO9 $end
   $var wire  1 : RX $end
   $var wire  8 . RXbuffer [7:0] $end
   $var wire  1 / RXready $end
   $var wire  1 ; TX $end
   $var wire  8 # TXbuffer [7:0] $end
   $var wire  1 0 TXbusy $end
   $var wire  1 $ TXstart $end
   $var wire 16 % a [15:0] $end
   $var wire 16 & b [15:0] $end
   $var wire 25 + clkdiv [24:0] $end
   $var wire  2 ' op [1:0] $end
   $var wire  1 ) overflow $end
   $var wire 16 ( res [15:0] $end
   $var wire  4 * testState [3:0] $end
   $scope module ALU $end
    $var wire  1 9 CLK $end
    $var wire 16 % a [15:0] $end
    $var wire 17 , addsub [16:0] $end
    $var wire 16 & b [15:0] $end
    $var wire 17 - mult [16:0] $end
    $var wire  2 ' op [1:0] $end
    $var wire  1 ) overflow $end
    $var wire 16 ( res [15:0] $end
   $upscope $end
   $scope module FTDI $end
    $var wire  1 9 CLK $end
    $var wire 32 B CLOCK_DIVISOR [31:0] $end
    $var wire  1 : RX $end
    $var wire  8 . RXbuffer [7:0] $end
    $var wire  1 / RXready $end
    $var wire  4 6 RXstate [3:0] $end
    $var wire  1 ; TX $end
    $var wire  8 # TXbuffer [7:0] $end
    $var wire  1 0 TXbusy $end
    $var wire  1 4 TXready $end
    $var wire  8 5 TXshift [7:0] $end
    $var wire  1 $ TXstart $end
    $var wire  4 3 TXstate [3:0] $end
    $var wire  3 1 baudAcc [2:0] $end
    $var wire  1 2 baudTick $end
    $var wire  3 7 gap [2:0] $end
    $var wire  1 8 nextBit $end
   $upscope $end
  $upscope $end
 $upscope $end
$enddefinitions $end


#666
b00000000 #
0$
b0000000000000000 %
b0001000000000000 &
b10 '
b0000000000000000 (
0)
b0000 *
b0000000000000000000000000 +
b00001000000000000 ,
b00000000000000000 -
b00000000 .
0/
00
b000 1
02
b0000 3
14
b00000000 5
b0000 6
b000 7
08
09
1:
1;
0<
0=
0>
0?
1@
0A
b00000000000000000000000000000010 B
#833
b0000000000000000000000001 +
19
#1250
09
#1499
#1666
b0000000000000000000000010 +
19
#2083
09
#2333
#2500
b0000000000000000000000011 +
19
#2916
09
#3166
#3333
b0000000000000000000000100 +
19
#3749
09
#3999
0:
#4166
b0000000000000000000000101 +
19
#4583
b1000 6
09
#4833
#5000
b0000000000000000000000110 +
19
#5416
b001 7
09
#5666
#5833
b0000000000000000000000111 +
19
#6249
b010 7
09
#6499
#6666
b0000000000000000000001000 +
19
#7083
b011 7
09
#7333
#7500
b0000000000000000000001001 +
19
#7916
b100 7
18
09
#8166
#8333
b0000000000000000000001010 +
19
#8749
b1001 6
b001 7
08
09
#9000
#9166
b0000000000000000000001011 +
19
#9583
b010 7
09
#9833
#10000
b0000000000000000000001100 +
19
#10416
b011 7
09
#10666
1:
#10833
b0000000000000000000001101 +
19
#11249
b100 7
18
09
#11499
#11666
b0000000000000000000001110 +
19
#12083
b10000000 .
b1010 6
b001 7
08
09
#12333
#12500
b0000000000000000000001111 +
19
#12916
b010 7
09
#13166
#13333
b0000000000000000000010000 +
19
#13749
b011 7
09
#13999
0:
#14166
b0000000000000000000010001 +
19
#14583
b100 7
18
09
#14833
#15000
b0000000000000000000010010 +
19
#15416
b01000000 .
b1011 6
b001 7
08
09
#15666
#15833
b0000000000000000000010011 +
19
#16249
b010 7
09
#16499
#16666
b0000000000000000000010100 +
19
#17083
b011 7
09
#17333
#17500
b0000000000000000000010101 +
19
#17916
b100 7
18
09
#18166
#18333
b0000000000000000000010110 +
19
#18750
b00100000 .
b1100 6
b001 7
08
09
#18999
#19166
b0000000000000000000010111 +
19
#19583
b010 7
09
#19833
#20000
b0000000000000000000011000 +
19
#20416
b011 7
09
#20666
#20833
b0000000000000000000011001 +
19
#21249
b100 7
18
09
#21499
#21666
b0000000000000000000011010 +
19
#22083
b00010000 .
b1101 6
b001 7
08
09
#22333
#22500
b0000000000000000000011011 +
19
#22916
b010 7
09
#23166
#23333
b0000000000000000000011100 +
19
#23749
b011 7
09
#23999
#24166
b0000000000000000000011101 +
19
#24583
b100 7
18
09
#24833
#25000
b0000000000000000000011110 +
19
#25416
b00001000 .
b1110 6
b001 7
08
09
#25666
#25833
b0000000000000000000011111 +
19
#26249
b010 7
09
#26499
#26666
b0000000000000000000100000 +
19
#27083
b011 7
09
#27333
#27500
b0000000000000000000100001 +
19
#27916
b100 7
18
09
#28166
#28333
b0000000000000000000100010 +
19
#28749
b00000100 .
b1111 6
b001 7
08
09
#28999
#29166
b0000000000000000000100011 +
19
#29583
b010 7
09
#29833
#30000
b0000000000000000000100100 +
19
#30416
b011 7
09
#30666
#30833
b0000000000000000000100101 +
19
#31249
b100 7
18
09
#31499
#31666
b0000000000000000000100110 +
19
#32083
b00000010 .
b0001 6
b001 7
08
09
#32333
#32500
b0000000000000000000100111 +
19
#32916
b010 7
09
#33166
#33333
b0000000000000000000101000 +
19
#33749
b011 7
09
#34000
1:
#34166
b0000000000000000000101001 +
19
#34583
b100 7
18
09
#34833
#35000
b0000000000000000000101010 +
19
#35416
1/
b0000 6
b001 7
08
09
#35666
#35833
b0001 *
b0000000000000000000101011 +
19
#36249
0/
b000 7
09
#36500
#36666
b0000000000000000000101100 +
19
#37083
09
#37333
0:
#37500
b0000000000000000000101101 +
19
#37916
b1000 6
09
#38166
#38333
b0000000000000000000101110 +
19
#38749
b001 7
09
#39000
#39166
b0000000000000000000101111 +
19
#39583
b010 7
09
#39833
#40000
b0000000000000000000110000 +
19
#40416
b011 7
09
#40666
#40833
b0000000000000000000110001 +
19
#41249
b100 7
18
09
#41499
#41666
b0000000000000000000110010 +
19
#42083
b00000001 .
b1001 6
b001 7
08
09
#42333
#42500
b0000000000000000000110011 +
19
#42916
b010 7
09
#43166
#43333
b0000000000000000000110100 +
19
#43749
b011 7
09
#43999
1:
#44166
b0000000000000000000110101 +
19
#44583
b100 7
18
09
#44833
#45000
b0000000000000000000110110 +
19
#45416
b10000000 .
b1010 6
b001 7
08
09
#45666
#45833
b0000000000000000000110111 +
19
#46249
b010 7
09
#46499
#46666
b0000000000000000000111000 +
19
#47083
b011 7
09
#47333
#47500
b0000000000000000000111001 +
19
#47916
b100 7
18
09
#48166
#48333
b0000000000000000000111010 +
19
#48749
b11000000 .
b1011 6
b001 7
08
09
#48999
#49166
b0000000000000000000111011 +
19
#49583
b010 7
09
#49833
#50000
b0000000000000000000111100 +
19
#50416
b011 7
09
#50666
#50833
b0000000000000000000111101 +
19
#51249
b100 7
18
09
#51499
#51666
b0000000000000000000111110 +
19
#52083
b11100000 .
b1100 6
b001 7
08
09
#52333
#52500
b0000000000000000000111111 +
19
#52916
b010 7
09
#53166
#53333
b0000000000000000001000000 +
19
#53749
b011 7
09
#53999
#54166
b0000000000000000001000001 +
19
#54583
b100 7
18
09
#54833
#55000
b0000000000000000001000010 +
19
#55416
b11110000 .
b1101 6
b001 7
08
09
#55666
#55833
b0000000000000000001000011 +
19
#56249
b010 7
09
#56499
#56666
b0000000000000000001000100 +
19
#57083
b011 7
09
#57333
0:
#57500
b0000000000000000001000101 +
19
#57916
b100 7
18
09
#58166
#58333
b0000000000000000001000110 +
19
#58749
b01111000 .
b1110 6
b001 7
08
09
#58999
#59166
b0000000000000000001000111 +
19
#59583
b010 7
09
#59833
#60000
b0000000000000000001001000 +
19
#60416
b011 7
09
#60666
#60833
b0000000000000000001001001 +
19
#61249
b100 7
18
09
#61499
#61666
b0000000000000000001001010 +
19
#62083
b00111100 .
b1111 6
b001 7
08
09
#62333
#62500
b0000000000000000001001011 +
19
#62916
b010 7
09
#63166
#63333
b0000000000000000001001100 +
19
#63749
b011 7
09
#63999
#64166
b0000000000000000001001101 +
19
#64583
b100 7
18
09
#64833
#65000
b0000000000000000001001110 +
19
#65416
b00011110 .
b0001 6
b001 7
08
09
#65666
#65833
b0000000000000000001001111 +
19
#66250
b010 7
09
#66499
#66666
b0000000000000000001010000 +
19
#67083
b011 7
09
#67333
1:
#67500
b0000000000000000001010001 +
19
#67916
b100 7
18
09
#68166
#68333
b0000000000000000001010010 +
19
#68750
1/
b0000 6
b001 7
08
09
#68999
#69166
b0000000000011110 %
b0010 *
b0000000000000000001010011 +
b00001000000011110 ,
b11110000000000000 -
19
#69583
0/
b000 7
09
#69833
#70000
b1110000000000000 (
1)
b0000000000000000001010100 +
19
#70416
09
#70666
0:
#70833
b0000000000000000001010101 +
19
#71250
b1000 6
09
#71499
#71666
b0000000000000000001010110 +
19
#72083
b001 7
09
#72333
#72500
b0000000000000000001010111 +
19
#72916
b010 7
09
#73166
#73333
b0000000000000000001011000 +
19
#73750
b011 7
09
#73999
#74166
b0000000000000000001011001 +
19
#74583
b100 7
18
09
#74833
#75000
b0000000000000000001011010 +
19
#75416
b00001111 .
b1001 6
b001 7
08
09
#75666
#75833
b0000000000000000001011011 +
19
#76250
b010 7
09
#76499
#76666
b0000000000000000001011100 +
19
#77083
b011 7
09
#77333
#77500
b0000000000000000001011101 +
19
#77916
b100 7
18
09
#78166
#78333
b0000000000000000001011110 +
19
#78750
b00000111 .
b1010 6
b001 7
08
09
#78999
#79166
b0000000000000000001011111 +
19
#79583
b010 7
09
#79833
#80000
b0000000000000000001100000 +
19
#80416
b011 7
09
#80666
#80833
b0000000000000000001100001 +
19
#81250
b100 7
18
09
#81499
#81666
b0000000000000000001100010 +
19
#82083
b00000011 .
b1011 6
b001 7
08
09
#82333
#82500
b0000000000000000001100011 +
19
#82916
b010 7
09
#83166
#83333
b0000000000000000001100100 +
19
#83749
b011 7
09
#83999
#84166
b0000000000000000001100101 +
19
#84583
b100 7
18
09
#84833
#85000
b0000000000000000001100110 +
19
#85416
b00000001 .
b1100 6
b001 7
08
09
#85666
#85833
b0000000000000000001100111 +
19
#86249
b010 7
09
#86499
#86666
b0000000000000000001101000 +
19
#87083
b011 7
09
#87333
#87500
b0000000000000000001101001 +
19
#87916
b100 7
18
09
#88166
#88333
b0000000000000000001101010 +
19
#88749
b00000000 .
b1101 6
b001 7
08
09
#88999
#89166
b0000000000000000001101011 +
19
#89583
b010 7
09
#89833
#90000
b0000000000000000001101100 +
19
#90416
b011 7
09
#90666
#90833
b0000000000000000001101101 +
19
#91249
b100 7
18
09
#91499
#91666
b0000000000000000001101110 +
19
#92083
b1110 6
b001 7
08
09
#92333
#92500
b0000000000000000001101111 +
19
#92916
b010 7
09
#93166
#93333
b0000000000000000001110000 +
19
#93749
b011 7
09
#93999
#94166
b0000000000000000001110001 +
19
#94583
b100 7
18
09
#94833
#95000
b0000000000000000001110010 +
19
#95416
b1111 6
b001 7
08
09
#95666
#95833
b0000000000000000001110011 +
19
#96249
b010 7
09
#96499
#96666
b0000000000000000001110100 +
19
#97083
b011 7
09
#97333
#97500
b0000000000000000001110101 +
19
#97916
b100 7
18
09
#98166
#98333
b0000000000000000001110110 +
19
#98749
b0001 6
b001 7
08
09
#98999
#99166
b0000000000000000001110111 +
19
#99583
b010 7
09
#99833
#100000
b0000000000000000001111000 +
19
#100416
b011 7
09
#100666
1:
#100833
b0000000000000000001111001 +
19
#101249
b100 7
18
09
#101499
#101666
b0000000000000000001111010 +
19
#102083
1/
b0000 6
b001 7
08
09
#102333
#102500
b0011 *
b0000000000000000001111011 +
19
#102916
0/
b000 7
09
#103166
#103333
b0000000000000000001111100 +
19
#103749
09
#103999
0:
#104166
b0000000000000000001111101 +
19
#104583
b1000 6
09
#104833
#105000
b0000000000000000001111110 +
19
#105416
b001 7
09
#105666
#105833
b0000000000000000001111111 +
19
#106249
b010 7
09
#106499
#106666
b0000000000000000010000000 +
19
#107083
b011 7
09
#107333
#107500
b0000000000000000010000001 +
19
#107916
b100 7
18
09
#108166
#108333
b0000000000000000010000010 +
19
#108749
b1001 6
b001 7
08
09
#108999
#109166
b0000000000000000010000011 +
19
#109583
b010 7
09
#109833
#110000
b0000000000000000010000100 +
19
#110416
b011 7
09
#110666
#110833
b0000000000000000010000101 +
19
#111249
b100 7
18
09
#111499
#111666
b0000000000000000010000110 +
19
#112083
b1010 6
b001 7
08
09
#112333
#112500
b0000000000000000010000111 +
19
#112916
b010 7
09
#113166
#113333
b0000000000000000010001000 +
19
#113749
b011 7
09
#113999
1:
#114166
b0000000000000000010001001 +
19
#114583
b100 7
18
09
#114833
#115000
b0000000000000000010001010 +
19
#115416
b10000000 .
b1011 6
b001 7
08
09
#115666
#115833
b0000000000000000010001011 +
19
#116249
b010 7
09
#116499
#116666
b0000000000000000010001100 +
19
#117083
b011 7
09
#117333
#117500
b0000000000000000010001101 +
19
#117916
b100 7
18
09
#118166
#118333
b0000000000000000010001110 +
19
#118749
b11000000 .
b1100 6
b001 7
08
09
#118999
#119166
b0000000000000000010001111 +
19
#119583
b010 7
09
#119833
#120000
b0000000000000000010010000 +
19
#120416
b011 7
09
#120666
0:
#120833
b0000000000000000010010001 +
19
#121249
b100 7
18
09
#121499
#121666
b0000000000000000010010010 +
19
#122083
b01100000 .
b1101 6
b001 7
08
09
#122333
#122500
b0000000000000000010010011 +
19
#122916
b010 7
09
#123166
#123333
b0000000000000000010010100 +
19
#123749
b011 7
09
#123999
1:
#124166
b0000000000000000010010101 +
19
#124583
b100 7
18
09
#124833
#125000
b0000000000000000010010110 +
19
#125416
b10110000 .
b1110 6
b001 7
08
09
#125666
#125833
b0000000000000000010010111 +
19
#126249
b010 7
09
#126499
#126666
b0000000000000000010011000 +
19
#127083
b011 7
09
#127333
0:
#127500
b0000000000000000010011001 +
19
#127916
b100 7
18
09
#128166
#128333
b0000000000000000010011010 +
19
#128749
b01011000 .
b1111 6
b001 7
08
09
#128999
#129166
b0000000000000000010011011 +
19
#129583
b010 7
09
#129833
#130000
b0000000000000000010011100 +
19
#130416
b011 7
09
#130666
#130833
b0000000000000000010011101 +
19
#131249
b100 7
18
09
#131500
#131666
b0000000000000000010011110 +
19
#132083
b00101100 .
b0001 6
b001 7
08
09
#132333
#132500
b0000000000000000010011111 +
19
#132916
b010 7
09
#133166
#133333
b0000000000000000010100000 +
19
#133749
b011 7
09
#134000
1:
#134166
b0000000000000000010100001 +
19
#134583
b100 7
18
09
#134833
#135000
b0000000000000000010100010 +
19
#135416
1/
b0000 6
b001 7
08
09
#135666
#135833
b0001000000101100 &
b0100 *
b0000000000000000010100011 +
b00001000001001010 ,
b11110010100101000 -
19
#136249
0/
b000 7
09
#136500
#136666
b1110010100101000 (
b0000000000000000010100100 +
19
#137083
09
#137333
0:
#137500
b0000000000000000010100101 +
19
#137916
b1000 6
09
#138166
#138333
b0000000000000000010100110 +
19
#138749
b001 7
09
#139000
#139166
b0000000000000000010100111 +
19
#139583
b010 7
09
#139833
#140000
b0000000000000000010101000 +
19
#140416
b011 7
09
#140666
1:
#140833
b0000000000000000010101001 +
19
#141249
b100 7
18
09
#141500
#141666
b0000000000000000010101010 +
19
#142083
b10010110 .
b1001 6
b001 7
08
09
#142333
#142500
b0000000000000000010101011 +
19
#142916
b010 7
09
#143166
#143333
b0000000000000000010101100 +
19
#143749
b011 7
09
#144000
0:
#144166
b0000000000000000010101101 +
19
#144583
b100 7
18
09
#144833
#145000
b0000000000000000010101110 +
19
#145416
b01001011 .
b1010 6
b001 7
08
09
#145666
#145833
b0000000000000000010101111 +
19
#146249
b010 7
09
#146500
#146666
b0000000000000000010110000 +
19
#147083
b011 7
09
#147333
#147500
b0000000000000000010110001 +
19
#147916
b100 7
18
09
#148166
#148333
b0000000000000000010110010 +
19
#148749
b00100101 .
b1011 6
b001 7
08
09
#149000
#149166
b0000000000000000010110011 +
19
#149583
b010 7
09
#149833
#150000
b0000000000000000010110100 +
19
#150416
b011 7
09
#150666
#150833
b0000000000000000010110101 +
19
#151249
b100 7
18
09
#151500
#151666
b0000000000000000010110110 +
19
#152083
b00010010 .
b1100 6
b001 7
08
09
#152333
#152500
b0000000000000000010110111 +
19
#152916
b010 7
09
#153166
#153333
b0000000000000000010111000 +
19
#153749
b011 7
09
#154000
#154166
b0000000000000000010111001 +
19
#154583
b100 7
18
09
#154833
#155000
b0000000000000000010111010 +
19
#155416
b00001001 .
b1101 6
b001 7
08
09
#155666
#155833
b0000000000000000010111011 +
19
#156249
b010 7
09
#156500
#156666
b0000000000000000010111100 +
19
#157083
b011 7
09
#157333
#157500
b0000000000000000010111101 +
19
#157916
b100 7
18
09
#158166
#158333
b0000000000000000010111110 +
19
#158749
b00000100 .
b1110 6
b001 7
08
09
#159000
#159166
b0000000000000000010111111 +
19
#159583
b010 7
09
#159833
#160000
b0000000000000000011000000 +
19
#160416
b011 7
09
#160666
#160833
b0000000000000000011000001 +
19
#161249
b100 7
18
09
#161500
#161666
b0000000000000000011000010 +
19
#162083
b00000010 .
b1111 6
b001 7
08
09
#162333
#162499
b0000000000000000011000011 +
19
#162916
b010 7
09
#163166
#163333
b0000000000000000011000100 +
19
#163749
b011 7
09
#163999
#164166
b0000000000000000011000101 +
19
#164583
b100 7
18
09
#164833
#165000
b0000000000000000011000110 +
19
#165416
b00000001 .
b0001 6
b001 7
08
09
#165666
#165833
b0000000000000000011000111 +
19
#166249
b010 7
09
#166499
#166666
b0000000000000000011001000 +
19
#167083
b011 7
09
#167333
1:
#167500
b0000000000000000011001001 +
19
#167916
b100 7
18
09
#168166
#168333
b0000000000000000011001010 +
19
#168749
1/
b0000 6
b001 7
08
09
#168999
#169166
b0000000100101100 &
b0101 *
b0000000000000000011001011 +
b00000000101001010 ,
b00010001100101000 -
19
#169583
0/
b000 7
09
#169833
#170000
b00101000 #
1$
b0010001100101000 (
0)
b0110 *
b0000000000000000011001100 +
19
#170416
10
b0100 3
04
b00101000 5
09
0;
#170666
#170833
0$
b0000000000000000011001101 +
19
#171249
b001 1
09
#171499
#171666
b0000000000000000011001110 +
19
#172083
b010 1
09
#172333
#172500
b0000000000000000011001111 +
19
#172916
b011 1
09
#173166
#173333
b0000000000000000011010000 +
19
#173749
b100 1
12
09
#173999
#174166
b0000000000000000011010001 +
19
#174583
b001 1
02
b1000 3
09
#174833
#175000
b0000000000000000011010010 +
19
#175416
b010 1
09
#175666
#175833
b0000000000000000011010011 +
19
#176249
b011 1
09
#176499
#176666
b0000000000000000011010100 +
19
#177083
b100 1
12
09
#177333
#177500
b0000000000000000011010101 +
19
#177916
b001 1
02
b1001 3
b00010100 5
09
#178166
#178333
b0000000000000000011010110 +
19
#178749
b010 1
09
#178999
#179166
b0000000000000000011010111 +
19
#179583
b011 1
09
#179833
#180000
b0000000000000000011011000 +
19
#180416
b100 1
12
09
#180666
#180833
b0000000000000000011011001 +
19
#181249
b001 1
02
b1010 3
b00001010 5
09
#181499
#181666
b0000000000000000011011010 +
19
#182083
b010 1
09
#182333
#182500
b0000000000000000011011011 +
19
#182916
b011 1
09
#183166
#183333
b0000000000000000011011100 +
19
#183749
b100 1
12
09
#183999
#184166
b0000000000000000011011101 +
19
#184583
b001 1
02
b1011 3
b00000101 5
09
1;
#184833
#185000
b0000000000000000011011110 +
19
#185416
b010 1
09
#185666
#185833
b0000000000000000011011111 +
19
#186249
b011 1
09
#186499
#186666
b0000000000000000011100000 +
19
#187083
b100 1
12
09
#187333
#187500
b0000000000000000011100001 +
19
#187916
b001 1
02
b1100 3
b00000010 5
09
0;
#188166
#188333
b0000000000000000011100010 +
19
#188749
b010 1
09
#188999
#189166
b0000000000000000011100011 +
19
#189583
b011 1
09
#189833
#190000
b0000000000000000011100100 +
19
#190416
b100 1
12
09
#190666
#190833
b0000000000000000011100101 +
19
#191249
b001 1
02
b1101 3
b00000001 5
09
1;
#191499
#191666
b0000000000000000011100110 +
19
#192083
b010 1
09
#192333
#192500
b0000000000000000011100111 +
19
#192916
b011 1
09
#193166
#193333
b0000000000000000011101000 +
19
#193749
b100 1
12
09
#193999
#194166
b0000000000000000011101001 +
19
#194583
b001 1
02
b1110 3
b00000000 5
09
0;
#194833
#195000
b0000000000000000011101010 +
19
#195416
b010 1
09
#195666
#195833
b0000000000000000011101011 +
19
#196249
b011 1
09
#196499
#196666
b0000000000000000011101100 +
19
#197083
b100 1
12
09
#197333
#197500
b0000000000000000011101101 +
19
#197916
b001 1
02
b1111 3
09
#198166
#198333
b0000000000000000011101110 +
19
#198749
b010 1
09
#198999
#199166
b0000000000000000011101111 +
19
#199583
b011 1
09
#199833
#200000
b0000000000000000011110000 +
19
#200416
b100 1
12
09
#200666
#200833
b0000000000000000011110001 +
19
#201249
b001 1
02
b0001 3
09
1;
#201499
#201666
b0000000000000000011110010 +
19
#202083
b010 1
09
#202333
#202500
b0000000000000000011110011 +
19
#202916
b011 1
09
#203166
#203333
b0000000000000000011110100 +
19
#203749
b100 1
12
09
#203999
#204166
b0000000000000000011110101 +
19
#204583
00
b001 1
02
b0000 3
14
09
#204833
#205000
b00100011 #
1$
b0111 *
b0000000000000000011110110 +
19
#205416
10
b000 1
b0100 3
04
b00100011 5
09
0;
#205666
#205833
0$
b0000000000000000011110111 +
19
#206249
b001 1
09
#206499
#206666
b0000000000000000011111000 +
19
#207083
b010 1
09
#207333
#207500
b0000000000000000011111001 +
19
#207916
b011 1
09
#208166
#208333
b0000000000000000011111010 +
19
#208749
b100 1
12
09
#208999
#209166
b0000000000000000011111011 +
19
#209583
b001 1
02
b1000 3
09
1;
#209833
#210000
b0000000000000000011111100 +
19
#210416
b010 1
09
#210666
#210833
b0000000000000000011111101 +
19
#211249
b011 1
09
#211499
#211666
b0000000000000000011111110 +
19
#212083
b100 1
12
09
#212333
#212500
b0000000000000000011111111 +
19
#212916
b001 1
02
b1001 3
b00010001 5
09
#213166
#213333
b0000000000000000100000000 +
19
#213749
b010 1
09
#213999
#214166
b0000000000000000100000001 +
19
#214583
b011 1
09
#214833
#215000
b0000000000000000100000010 +
19
#215416
b100 1
12
09
#215666
#215833
b0000000000000000100000011 +
19
#216249
b001 1
02
b1010 3
b00001000 5
09
0;
#216499
#216666
b0000000000000000100000100 +
19
#217083
b010 1
09
#217333
#217500
b0000000000000000100000101 +
19
#217916
b011 1
09
#218166
#218333
b0000000000000000100000110 +
19
#218749
b100 1
12
09
#218999
#219166
b0000000000000000100000111 +
19
#219583
b001 1
02
b1011 3
b00000100 5
09
#219833
#220000
b0000000000000000100001000 +
19
#220416
b010 1
09
#220666
#220833
b0000000000000000100001001 +
19
#221249
b011 1
09
#221499
#221666
b0000000000000000100001010 +
19
#222083
b100 1
12
09
#222333
#222500
b0000000000000000100001011 +
19
#222916
b001 1
02
b1100 3
b00000010 5
09
#223166
#223333
b0000000000000000100001100 +
19
#223749
b010 1
09
#223999
#224166
b0000000000000000100001101 +
19
#224583
b011 1
09
#224833
#225000
b0000000000000000100001110 +
19
#225416
b100 1
12
09
#225666
#225833
b0000000000000000100001111 +
19
#226249
b001 1
02
b1101 3
b00000001 5
09
1;
#226499
#226666
b0000000000000000100010000 +
19
#227083
b010 1
09
#227333
