verilog/alu.v
// this aboutta get complicated

module alu(
    input wire CLK,

    input wire [2:0] aindex,
    input wire [2:0] bindex,
    input wire [2:0] yindex,
    input wire [1:0] op, // don't forget we need logic!

    output reg overflow = 0
  );

  reg [15:0] r0 = 16'b1;
  reg [15:0] r1 = 16'b1;
  reg [15:0] r2 = 16'b1;
  reg [15:0] r3 = 16'b1;
  reg [15:0] r4 = 16'b1;
  reg [15:0] r5 = 16'b1;
  reg [15:0] r6 = 16'b1;
  reg [15:0] r7 = 16'b1;

  wire [16:0] addsub; // wire with overflow bit
  wire [16:0] mult; // the overflow bit works just like addition

  reg [15:0] a = 16'b0;
  reg [15:0] b = 16'b0;

  always @(*) begin
    case (aindex)
      3'd0: a = r0;
      3'd1: a = r1;
      3'd2: a = r2;
      3'd3: a = r3;
      3'd4: a = r4;
      3'd5: a = r5;
      3'd6: a = r6;
      3'd7: a = r7;
    endcase
  end

  always @(*) begin
    case (bindex)
      3'd0: b = r0;
      3'd1: b = r1;
      3'd2: b = r2;
      3'd3: b = r3;
      3'd4: b = r4;
      3'd5: b = r5;
      3'd6: b = r6;
      3'd7: b = r7;
    endcase
  end

  assign addsub = op[0] ? a - b : a + b;
  assign mult = a*b;

  always @(posedge CLK) begin
    if (~op[1]) begin
      case (yindex)
        3'd0: r0 <= addsub[15:0];
        3'd1: r1 <= addsub[15:0];
        3'd2: r2 <= addsub[15:0];
        3'd3: r3 <= addsub[15:0];
        3'd4: r4 <= addsub[15:0];
        3'd5: r5 <= addsub[15:0];
        3'd6: r6 <= addsub[15:0];
        3'd7: r7 <= addsub[15:0];
      endcase
      overflow <= addsub[16];
    end else begin
      case (yindex)
        3'd0: r0 <= mult[15:0];
        3'd1: r1 <= mult[15:0];
        3'd2: r2 <= mult[15:0];
        3'd3: r3 <= mult[15:0];
        3'd4: r4 <= mult[15:0];
        3'd5: r5 <= mult[15:0];
        3'd6: r6 <= mult[15:0];
        3'd7: r7 <= mult[15:0];
      endcase
      overflow <= mult[16];
    end
  end

endmodule

verilog/uart.v
//parameter ClkFrequency = 12000000
//parameter Baud = 3000000
// 8 data bits, 1 stop bit, no parity

module uart(
    input CLK,
    input RX,
    input [7:0] TXbuffer,
    input TXstart,

    output TX,
    output reg [7:0] RXbuffer = 0,
    output reg RXready = 0,
    output TXbusy
  );

  parameter CLOCK_DIVISOR = 2; // 2 ^ CLOCK_DIVISOR

  // TRANSMITTER

  reg [CLOCK_DIVISOR:0] baudAcc = 0;
  wire baudTick = baudAcc[CLOCK_DIVISOR];

  reg [3:0] TXstate = 0;
  wire TXready = (TXstate==0);
  assign TXbusy = ~TXready;

  reg [7:0] TXshift = 0;

  always @(negedge CLK) begin

    if(TXready & TXstart) TXshift <= TXbuffer;
    else if(TXstate[3] & baudTick) TXshift <= (TXshift >> 1);

    if (TXstate == 4'b0000) baudAcc <= 0;
    else baudAcc <= baudAcc[CLOCK_DIVISOR - 1:0] + 1'b1;

    case(TXstate)
      4'b0000: if(TXstart)  TXstate <= 4'b0100;
      4'b0100: if(baudTick) TXstate <= 4'b1000; // start bit
      4'b1000: if(baudTick) TXstate <= 4'b1001; // bit 0
      4'b1001: if(baudTick) TXstate <= 4'b1010; // bit 1
      4'b1010: if(baudTick) TXstate <= 4'b1011; // bit 2
      4'b1011: if(baudTick) TXstate <= 4'b1100; // bit 3
      4'b1100: if(baudTick) TXstate <= 4'b1101; // bit 4
      4'b1101: if(baudTick) TXstate <= 4'b1110; // bit 5
      4'b1110: if(baudTick) TXstate <= 4'b1111; // bit 6
      4'b1111: if(baudTick) TXstate <= 4'b0001; // bit 7
      4'b0001: if(baudTick) TXstate <= 4'b0000; // stop bit
      default: if(baudTick) TXstate <= 4'b0000;
    endcase
  end

  assign TX = (TXstate < 4) | (TXstate[3] & TXshift[0]);

  // RECIEVER

  // Oversampling x 4 (i.e. every clock cycle)
  // Surprisingly reliable

  reg [3:0] RXstate = 0;
  reg [CLOCK_DIVISOR:0] gap = 0;

  wire nextBit = gap[CLOCK_DIVISOR];

  always @(negedge CLK) begin

    case (RXstate)
      4'b0000: if (~RX) RXstate <= 4'b1000;     // start bit found
      4'b1000: if (nextBit) RXstate <= 4'b1001; // bit 0
      4'b1001: if (nextBit) RXstate <= 4'b1010; // bit 1
      4'b1010: if (nextBit) RXstate <= 4'b1011; // bit 2
      4'b1011: if (nextBit) RXstate <= 4'b1100; // bit 3
      4'b1100: if (nextBit) RXstate <= 4'b1101; // bit 4
      4'b1101: if (nextBit) RXstate <= 4'b1110; // bit 5
      4'b1110: if (nextBit) RXstate <= 4'b1111; // bit 6
      4'b1111: if (nextBit) RXstate <= 4'b0001; // bit 7
      4'b0001: if (nextBit) RXstate <= 4'b0000; // stop bit
      default: RXstate <= 4'b0000;
    endcase

    if (RXstate == 4'b0000) begin
      gap <= 0;
    end else gap <= gap[CLOCK_DIVISOR - 1:0] + 1'b1;

    if (nextBit && RXstate[3]) RXbuffer <= {RX, RXbuffer[7:1]};
    RXready <= (nextBit && RXstate == 4'b0001);
  end

endmodule

verilog/top.v
//verilator lint_off UNUSED

`timescale 1ns/100ps
`default_nettype none

`include "uart.v"
`include "alu.v"

module top(
    input wire CLK,

    input wire RX,
    output wire TX,

    // output wire GPIO0,
    // output wire GPIO1,
    // output wire GPIO2,
    output wire GPIO3,
    output wire GPIO9,
    output wire GPIO11
  );

  // UART communication
  wire [7:0] RXbuffer;
  reg [7:0] TXbuffer = 0;
  reg TXstart = 0;
  wire RXready;
  wire TXbusy;

  uart FTDI(
      .CLK(CLK),
      .RX(RX),
      .TXbuffer(TXbuffer),
      .TXstart(TXstart),
      .TX(TX),
      .RXbuffer(RXbuffer),
      .RXready(RXready),
      .TXbusy(TXbusy)
    );

  // ALU
  reg [2:0] a = 0;
  reg [2:0] b = 3'b001;
  reg [2:0] y = 0;
  reg [1:0] op = 2'b0;
  //wire [15:0] res;
  wire overflow;

  alu ALU(
      .CLK(CLK),
      .aindex(a),
      .bindex(b),
      .yindex(y),
      .op(op),
      .overflow(overflow)
    );

  reg [3:0] testState = 0;
  reg [24:0] clkdiv = 0;

  always @(posedge CLK) begin

    clkdiv <= clkdiv + 1'b1;
    // testState <= testState + 1'b1;
    //
    if (clkdiv[3:0] == 4'd15) begin
      a <= a + 1'b1;
      y <= y + 1'b1;
      // a <= 0;
    end

  //   case (testState)
  //     4'd0:
  //       begin
  //         TXstart <= 1'b0;
  //         if (RXready) begin
  //           op <= RXbuffer[1:0];
  //           testState <= 4'd1;
  //         end
  //       end
  //     4'd1:
  //       begin
  //         if (RXready) begin
  //           a[7:0] <= RXbuffer;
  //           testState <= 4'd2;
  //         end
  //       end
  //     4'd2:
  //       begin
  //         if (RXready) begin
  //           a[15:8] <= RXbuffer;
  //           testState <= 4'd3;
  //         end
  //       end
  //     4'd3:
  //       begin
  //         if (RXready) begin
  //           b[7:0] <= RXbuffer;
  //           testState <= 4'd4;
  //         end
  //       end
  //     4'd4:
  //       begin
  //         if (RXready) begin
  //           b[15:8] <= RXbuffer;
  //           testState <= 4'd5;
  //         end
  //       end
  //     4'd5:
  //       begin
  //         if (~TXbusy) begin
  //           TXbuffer <= res[7:0];
  //           TXstart <= 1'b1;
  //           testState <= 4'd6;
  //         end
  //       end
  //     4'd6:
  //       begin
  //         TXstart <= 1'b0;
  //         if (~TXbusy) begin
  //           TXbuffer <= res[15:8];
  //           TXstart <= 1'b1;
  //           testState <= 4'd7;
  //         end
  //       end
  //     4'd7:
  //       begin
  //         TXstart <= 1'b0;
  //         if (~TXbusy) begin
  //           TXbuffer <= {7'd0, overflow};
  //           TXstart <= 1'b1;
  //           testState <= 4'd0;
  //         end
  //       end
  //     default:
  //       begin
  //         TXstart <= 1'b0;
  //         testState <= 4'd0;
  //       end
  //   endcase
   end

  assign GPIO9 = 1'b1;
  assign GPIO11 = 1'b0;

  // assign GPIO0 = res[0];
  // assign GPIO1 = res[1];
  // assign GPIO2 = res[2];
  assign GPIO3 = clkdiv[23];

endmodule

trace.vcd
$version Generated by VerilatedVcd $end
$date Sat Aug 15 01:31:08 2020
 $end
$timescale 100ps $end

 $scope module TOP $end
  $var wire  1 > CLK $end
  $var wire  1 C GPIO11 $end
  $var wire  1 A GPIO3 $end
  $var wire  1 B GPIO9 $end
  $var wire  1 ? RX $end
  $var wire  1 @ TX $end
  $scope module top $end
   $var wire  1 > CLK $end
   $var wire  1 C GPIO11 $end
   $var wire  1 A GPIO3 $end
   $var wire  1 B GPIO9 $end
   $var wire  1 ? RX $end
   $var wire  8 3 RXbuffer [7:0] $end
   $var wire  1 4 RXready $end
   $var wire  1 @ TX $end
   $var wire  8 D TXbuffer [7:0] $end
   $var wire  1 5 TXbusy $end
   $var wire  1 E TXstart $end
   $var wire  3 # a [2:0] $end
   $var wire  3 F b [2:0] $end
   $var wire 25 & clkdiv [24:0] $end
   $var wire  2 G op [1:0] $end
   $var wire  1 % overflow $end
   $var wire  4 H testState [3:0] $end
   $var wire  3 $ y [2:0] $end
   $scope module ALU $end
    $var wire  1 > CLK $end
    $var wire 16 1 a [15:0] $end
    $var wire 17 / addsub [16:0] $end
    $var wire  3 # aindex [2:0] $end
    $var wire 16 2 b [15:0] $end
    $var wire  3 F bindex [2:0] $end
    $var wire 17 0 mult [16:0] $end
    $var wire  2 G op [1:0] $end
    $var wire  1 % overflow $end
    $var wire 16 ' r0 [15:0] $end
    $var wire 16 ( r1 [15:0] $end
    $var wire 16 ) r2 [15:0] $end
    $var wire 16 * r3 [15:0] $end
    $var wire 16 + r4 [15:0] $end
    $var wire 16 , r5 [15:0] $end
    $var wire 16 - r6 [15:0] $end
    $var wire 16 . r7 [15:0] $end
    $var wire  3 $ yindex [2:0] $end
   $upscope $end
   $scope module FTDI $end
    $var wire  1 > CLK $end
    $var wire 32 I CLOCK_DIVISOR [31:0] $end
    $var wire  1 ? RX $end
    $var wire  8 3 RXbuffer [7:0] $end
    $var wire  1 4 RXready $end
    $var wire  4 ; RXstate [3:0] $end
    $var wire  1 @ TX $end
    $var wire  8 D TXbuffer [7:0] $end
    $var wire  1 5 TXbusy $end
    $var wire  1 9 TXready $end
    $var wire  8 : TXshift [7:0] $end
    $var wire  1 E TXstart $end
    $var wire  4 8 TXstate [3:0] $end
    $var wire  3 6 baudAcc [2:0] $end
    $var wire  1 7 baudTick $end
    $var wire  3 < gap [2:0] $end
    $var wire  1 = nextBit $end
   $upscope $end
  $upscope $end
 $upscope $end
$enddefinitions $end


#666
b000 #
b000 $
0%
b0000000000000000000000000 &
b0000000000000001 '
b0000000000000001 (
b0000000000000000 )
b0000000000000000 *
b0000000000000000 +
b0000000000000000 ,
b0000000000000000 -
b0000000000000000 .
b00000000000000010 /
b00000000000000001 0
b0000000000000001 1
b0000000000000001 2
b00000000 3
04
05
b000 6
07
b0000 8
19
b00000000 :
b0000 ;
b000 <
0=
0>
1?
1@
0A
1B
0C
b00000000 D
0E
b001 F
b00 G
b0000 H
b00000000000000000000000000000010 I
#833
b0000000000000000000000001 &
b0000000000000010 '
b00000000000000011 /
b00000000000000010 0
b0000000000000010 1
1>
#1250
0>
#1499
#1666
b0000000000000000000000010 &
b0000000000000011 '
b00000000000000100 /
b00000000000000011 0
b0000000000000011 1
1>
#2083
0>
#2333
#2500
b0000000000000000000000011 &
b0000000000000100 '
b00000000000000101 /
b00000000000000100 0
b0000000000000100 1
1>
#2916
0>
#3166
#3333
b0000000000000000000000100 &
b0000000000000101 '
b00000000000000110 /
b00000000000000101 0
b0000000000000101 1
1>
#3749
0>
#3999
#4166
b0000000000000000000000101 &
b0000000000000110 '
b00000000000000111 /
b00000000000000110 0
b0000000000000110 1
1>
#4583
0>
#4833
#5000
b0000000000000000000000110 &
b0000000000000111 '
b00000000000001000 /
b00000000000000111 0
b0000000000000111 1
1>
#5416
0>
#5666
#5833
b0000000000000000000000111 &
b0000000000001000 '
b00000000000001001 /
b00000000000001000 0
b0000000000001000 1
1>
#6249
0>
#6499
#6666
b0000000000000000000001000 &
b0000000000001001 '
b00000000000001010 /
b00000000000001001 0
b0000000000001001 1
1>
#7083
0>
#7333
#7500
b0000000000000000000001001 &
b0000000000001010 '
b00000000000001011 /
b00000000000001010 0
b0000000000001010 1
1>
#7916
0>
#8166
#8333
b0000000000000000000001010 &
b0000000000001011 '
b00000000000001100 /
b00000000000001011 0
b0000000000001011 1
1>
#8749
0>
#9000
#9166
b0000000000000000000001011 &
b0000000000001100 '
b00000000000001101 /
b00000000000001100 0
b0000000000001100 1
1>
#9583
0>
#9833
#10000
b0000000000000000000001100 &
b0000000000001101 '
b00000000000001110 /
b00000000000001101 0
b0000000000001101 1
1>
#10416
0>
#10666
#10833
b0000000000000000000001101 &
b0000000000001110 '
b00000000000001111 /
b00000000000001110 0
b0000000000001110 1
1>
#11249
0>
#11499
#11666
b0000000000000000000001110 &
b0000000000001111 '
b00000000000010000 /
b00000000000001111 0
b0000000000001111 1
1>
#12083
0>
#12333
#12500
b0000000000000000000001111 &
b0000000000010000 '
b00000000000010001 /
b00000000000010000 0
b0000000000010000 1
1>
#12916
0>
#13166
#13333
b001 #
b001 $
b0000000000000000000010000 &
b0000000000010001 '
b00000000000000010 /
b00000000000000001 0
b0000000000000001 1
1>
#13749
0>
#13999
#14166
b0000000000000000000010001 &
b0000000000000010 (
b00000000000000100 /
b00000000000000100 0
b0000000000000010 1
b0000000000000010 2
1>
#14583
0>
#14833
#15000
b0000000000000000000010010 &
b0000000000000100 (
b00000000000001000 /
b00000000000010000 0
b0000000000000100 1
b0000000000000100 2
1>
#15416
0>
#15666
#15833
b0000000000000000000010011 &
b0000000000001000 (
b00000000000010000 /
b00000000001000000 0
b0000000000001000 1
b0000000000001000 2
1>
#16249
0>
#16499
#16666
b0000000000000000000010100 &
b0000000000010000 (
b00000000000100000 /
b00000000100000000 0
b0000000000010000 1
b0000000000010000 2
1>
#17083
0>
#17333
#17500
b0000000000000000000010101 &
b0000000000100000 (
b00000000001000000 /
b00000010000000000 0
b0000000000100000 1
b0000000000100000 2
1>
#17916
0>
#18166
#18333
b0000000000000000000010110 &
b0000000001000000 (
b00000000010000000 /
b00001000000000000 0
b0000000001000000 1
b0000000001000000 2
1>
#18750
0>
#18999
#19166
b0000000000000000000010111 &
b0000000010000000 (
b00000000100000000 /
b00100000000000000 0
b0000000010000000 1
b0000000010000000 2
1>
#19583
0>
#19833
#20000
b0000000000000000000011000 &
b0000000100000000 (
b00000001000000000 /
b10000000000000000 0
b0000000100000000 1
b0000000100000000 2
1>
#20416
0>
#20666
#20833
b0000000000000000000011001 &
b0000001000000000 (
b00000010000000000 /
b00000000000000000 0
b0000001000000000 1
b0000001000000000 2
1>
#21249
0>
#21499
#21666
b0000000000000000000011010 &
b0000010000000000 (
b00000100000000000 /
b0000010000000000 1
b0000010000000000 2
1>
#22083
0>
#22333
#22500
b0000000000000000000011011 &
b0000100000000000 (
b00001000000000000 /
b0000100000000000 1
b0000100000000000 2
1>
#22916
0>
#23166
#23333
b0000000000000000000011100 &
b0001000000000000 (
b00010000000000000 /
b0001000000000000 1
b0001000000000000 2
1>
#23749
0>
#23999
#24166
b0000000000000000000011101 &
b0010000000000000 (
b00100000000000000 /
b0010000000000000 1
b0010000000000000 2
1>
#24583
0>
#24833
#25000
b0000000000000000000011110 &
b0100000000000000 (
b01000000000000000 /
b0100000000000000 1
b0100000000000000 2
1>
#25416
0>
#25666
#25833
b0000000000000000000011111 &
b1000000000000000 (
b10000000000000000 /
b1000000000000000 1
b1000000000000000 2
1>
#26249
0>
#26499
#26666
b010 #
b010 $
1%
b0000000000000000000100000 &
b0000000000000000 (
b00000000000000000 /
b0000000000000000 1
b0000000000000000 2
1>
#27083
0>
#27333
#27500
0%
b0000000000000000000100001 &
1>
#27916
0>
#28166
#28333
b0000000000000000000100010 &
1>
#28749
0>
#28999
#29166
b0000000000000000000100011 &
1>
#29583
0>
#29833
#30000
b0000000000000000000100100 &
1>
#30416
0>
#30666
#30833
b0000000000000000000100101 &
1>
#31249
0>
#31499
#31666
b0000000000000000000100110 &
1>
#32083
0>
#32333
#32500
b0000000000000000000100111 &
1>
#32916
0>
#33166
#33333
b0000000000000000000101000 &
1>
#33749
0>
#34000
#34166
b0000000000000000000101001 &
1>
#34583
0>
#34833
#35000
b0000000000000000000101010 &
1>
#35416
0>
#35666
#35833
b0000000000000000000101011 &
1>
#36249
0>
#36500
#36666
b0000000000000000000101100 &
1>
#37083
0>
#37333
#37500
b0000000000000000000101101 &
1>
#37916
0>
#38166
#38333
b0000000000000000000101110 &
1>
#38749
0>
#39000
#39166
b0000000000000000000101111 &
1>
#39583
0>
#39833
#40000
b011 #
b011 $
b0000000000000000000110000 &
1>
#40416
0>
#40666
#40833
b0000000000000000000110001 &
1>
#41249
0>
#41499
#41666
b0000000000000000000110010 &
1>
#42083
0>
#42333
#42500
b0000000000000000000110011 &
1>
#42916
0>
#43166
#43333
b0000000000000000000110100 &
1>
#43749
0>
#43999
#44166
b0000000000000000000110101 &
1>
#44583
0>
#44833
#45000
b0000000000000000000110110 &
1>
#45416
0>
#45666
#45833
b0000000000000000000110111 &
1>
#46249
0>
#46499
#46666
b0000000000000000000111000 &
1>
#47083
0>
#47333
#47500
b0000000000000000000111001 &
1>
#47916
0>
#48166
#48333
b0000000000000000000111010 &
1>
#48749
0>
#48999
#49166
b0000000000000000000111011 &
1>
#49583
0>
#49833
#50000
b0000000000000000000111100 &
1>
#50416
0>
#50666
#50833
b0000000000000000000111101 &
1>
#51249
0>
#51499
#51666
b0000000000000000000111110 &
1>
#52083
0>
#52333
#52500
b0000000000000000000111111 &
1>
#52916
0>
#53166
#53333
b100 #
b100 $
b0000000000000000001000000 &
1>
#53749
0>
#53999
#54166
b0000000000000000001000001 &
1>
#54583
0>
#54833
#55000
b0000000000000000001000010 &
1>
#55416
0>
#55666
#55833
b0000000000000000001000011 &
1>
#56249
0>
#56499
#56666
b0000000000000000001000100 &
1>
#57083
0>
#57333
#57500
b0000000000000000001000101 &
1>
#57916
0>
#58166
#58333
b0000000000000000001000110 &
1>
#58749
0>
#58999
#59166
b0000000000000000001000111 &
1>
#59583
0>
#59833
#60000
b0000000000000000001001000 &
1>
#60416
0>
#60666
#60833
b0000000000000000001001001 &
1>
#61249
0>
#61499
#61666
b0000000000000000001001010 &
1>
#62083
0>
#62333
#62500
b0000000000000000001001011 &
1>
#62916
0>
#63166
#63333
b0000000000000000001001100 &
1>
#63749
0>
#63999
#64166
b0000000000000000001001101 &
1>
#64583
0>
#64833
#65000
b0000000000000000001001110 &
1>
#65416
0>
#65666
#65833
b0000000000000000001001111 &
1>
#66250
0>
#66499
#66666
b101 #
b101 $
b0000000000000000001010000 &
1>
#67083
0>
#67333
#67500
b0000000000000000001010001 &
1>
#67916
0>
#68166
#68333
b0000000000000000001010010 &
1>
#68750
0>
#68999
#69166
b0000000000000000001010011 &
1>
#69583
0>
#69833
#70000
b0000000000000000001010100 &
1>
#70416
0>
#70666
#70833
b0000000000000000001010101 &
1>
#71250
0>
#71499
#71666
b0000000000000000001010110 &
1>
#72083
0>
#72333
#72500
b0000000000000000001010111 &
1>
#72916
0>
#73166
#73333
b0000000000000000001011000 &
1>
#73750
0>
#73999
#74166
b0000000000000000001011001 &
1>
#74583
0>
#74833
#75000
b0000000000000000001011010 &
1>
#75416
0>
#75666
#75833
b0000000000000000001011011 &
1>
#76250
0>
#76499
#76666
b0000000000000000001011100 &
1>
#77083
0>
#77333
#77500
b0000000000000000001011101 &
1>
#77916
0>
#78166
#78333
b0000000000000000001011110 &
1>
#78750
0>
#78999
#79166
b0000000000000000001011111 &
1>
#79583
0>
#79833
#80000
b110 #
b110 $
b0000000000000000001100000 &
1>
#80416
0>
#80666
#80833
b0000000000000000001100001 &
1>
#81250
0>
#81499
#81666
b0000000000000000001100010 &
1>
#82083
0>
#82333
#82500
b0000000000000000001100011 &
1>
#82916
0>
#83166
#83333
b0000000000000000001100100 &
1>
#83749
0>
#83999
#84166
b0000000000000000001100101 &
1>
#84583
0>
#84833
#85000
b0000000000000000001100110 &
1>
#85416
0>
#85666
#85833
b0000000000000000001100111 &
1>
#86249
0>
#86499
#86666
b0000000000000000001101000 &
1>
#87083
0>
#87333
#87500
b0000000000000000001101001 &
1>
#87916
0>
#88166
#88333
b0000000000000000001101010 &
1>
#88749
0>
#88999
#89166
b0000000000000000001101011 &
1>
#89583
0>
#89833
#90000
b0000000000000000001101100 &
1>
#90416
0>
#90666
#90833
b0000000000000000001101101 &
1>
#91249
0>
#91499
#91666
b0000000000000000001101110 &
1>
#92083
0>
#92333
#92500
b0000000000000000001101111 &
1>
#92916
0>
#93166
#93333
b111 #
b111 $
b0000000000000000001110000 &
1>
#93749
0>
#93999
#94166
b0000000000000000001110001 &
1>
#94583
0>
#94833
#95000
b0000000000000000001110010 &
1>
#95416
0>
#95666
#95833
b0000000000000000001110011 &
1>
#96249
0>
#96499
#96666
b0000000000000000001110100 &
1>
#97083
0>
#97333
#97500
b0000000000000000001110101 &
1>
#97916
0>
#98166
#98333
b0000000000000000001110110 &
1>
#98749
0>
#98999
#99166
b0000000000000000001110111 &
1>
#99583
0>
#99833
#100000
b0000000000000000001111000 &
1>
#100416
0>
#100666
#100833
b0000000000000000001111001 &
1>
#101249
0>
#101499
#101666
b0000000000000000001111010 &
1>
#102083
0>
#102333
#102500
b0000000000000000001111011 &
1>
#102916
0>
#103166
#103333
b0000000000000000001111100 &
1>
#103749
0>
#103999
#104166
b0000000000000000001111101 &
1>
#104583
0>
#104833
#105000
b0000000000000000001111110 &
1>
#105416
0>
#105666
#105833
b0000000000000000001111111 &
1>
#106249
0>
#106499
#106666
b000 #
b000 $
b0000000000000000010000000 &
b00000000000010001 /
b0000000000010001 1
1>
